gobbli/__init__.py
gobbli/cli.py
gobbli/docker.py
gobbli/io.py
gobbli/util.py
gobbli/augment/__init__.py
gobbli/augment/base.py
gobbli/augment/word2vec.py
gobbli/augment/wordnet.py
gobbli/augment/bert/Dockerfile
gobbli/augment/bert/__init__.py
gobbli/augment/bert/model.py
gobbli/augment/bert/src/augment_text.py
gobbli/augment/marian/Dockerfile
gobbli/augment/marian/__init__.py
gobbli/augment/marian/model.py
gobbli/augment/marian/src/backtranslate_text.py
gobbli/dataset/__init__.py
gobbli/dataset/base.py
gobbli/dataset/cmu_movie_summary.py
gobbli/dataset/imdb.py
gobbli/dataset/nested_file.py
gobbli/dataset/newsgroups.py
gobbli/dataset/trivial.py
gobbli/experiment/__init__.py
gobbli/experiment/base.py
gobbli/experiment/classification.py
gobbli/inspect/__init__.py
gobbli/inspect/evaluate.py
gobbli/interactive/evaluate.py
gobbli/interactive/explain.py
gobbli/interactive/explore.py
gobbli/interactive/util.py
gobbli/model/__init__.py
gobbli/model/base.py
gobbli/model/context.py
gobbli/model/majority.py
gobbli/model/mixin.py
gobbli/model/random.py
gobbli/model/bert/Dockerfile
gobbli/model/bert/__init__.py
gobbli/model/bert/model.py
gobbli/model/bert/src/__init__.py
gobbli/model/bert/src/create_pretraining_data.py
gobbli/model/bert/src/extract_features.py
gobbli/model/bert/src/modeling.py
gobbli/model/bert/src/modeling_test.py
gobbli/model/bert/src/optimization.py
gobbli/model/bert/src/optimization_test.py
gobbli/model/bert/src/requirements.txt
gobbli/model/bert/src/run_classifier.py
gobbli/model/bert/src/run_classifier_with_tfhub.py
gobbli/model/bert/src/run_pretraining.py
gobbli/model/bert/src/run_squad.py
gobbli/model/bert/src/tokenization.py
gobbli/model/bert/src/tokenization_test.py
gobbli/model/fasttext/Dockerfile
gobbli/model/fasttext/__init__.py
gobbli/model/fasttext/model.py
gobbli/model/mtdnn/Dockerfile
gobbli/model/mtdnn/__init__.py
gobbli/model/mtdnn/model.py
gobbli/model/mtdnn/src/gobbli_train.py
gobbli/model/mtdnn/src/prepro.py
gobbli-0.2.4.dist-info/LICENSE
gobbli-0.2.4.dist-info/METADATA
gobbli-0.2.4.dist-info/WHEEL
gobbli-0.2.4.dist-info/entry_points.txt
gobbli-0.2.4.dist-info/top_level.txt
gobbli-0.2.4.dist-info/RECORD
