Metadata-Version: 2.1
Name: gobbli
Version: 0.2.4
Summary: Uniform interface to deep learning approaches via Docker containers.
Home-page: https://github.com/RTIInternational/gobbli/
Author: RTI International
Maintainer: Jason Nance
License: LICENSE.txt
Platform: UNKNOWN
Classifier: Intended Audience :: Science/Research
Classifier: License :: OSI Approved :: Apache Software License
Classifier: Operating System :: MacOS :: MacOS X
Classifier: Operating System :: Microsoft :: Windows
Classifier: Operating System :: POSIX :: Linux
Classifier: Programming Language :: Python :: 3
Classifier: Programming Language :: Python :: 3.7
Classifier: Programming Language :: Python :: 3.8
Classifier: Topic :: Scientific/Engineering
Requires-Python: >=3.7
Requires-Dist: docker (>=3.7.0)
Requires-Dist: numpy (>=1.16.0)
Requires-Dist: pandas (>=0.24.0)
Requires-Dist: scikit-learn (>=0.22.0)
Requires-Dist: ray (>=0.8.4)
Requires-Dist: altair (>=3.2.0)
Requires-Dist: click (>=7.0)
Requires-Dist: humanize (>=1.1.0)
Provides-Extra: augment
Requires-Dist: nltk (>=3.4.4) ; extra == 'augment'
Requires-Dist: gensim (>=3.8.2) ; extra == 'augment'
Requires-Dist: spacy (>=2.1.4) ; extra == 'augment'
Provides-Extra: interactive
Requires-Dist: streamlit (>=0.56.0) ; extra == 'interactive'
Requires-Dist: gensim (>=3.8.2) ; extra == 'interactive'
Requires-Dist: umap-learn (>=0.3.10) ; extra == 'interactive'
Requires-Dist: eli5 (>=0.10.1) ; extra == 'interactive'
Requires-Dist: hdbscan (>=0.8.24) ; extra == 'interactive'
Provides-Extra: tokenize
Requires-Dist: sentencepiece (<0.1.90,>=0.1.83) ; extra == 'tokenize'
